quantastor/__init__.py
quantastor/qs_client.py
quantastor_pkg-1.0.9.data/scripts/qs_client.py
quantastor_pkg-1.0.9.dist-info/LICENSE
quantastor_pkg-1.0.9.dist-info/METADATA
quantastor_pkg-1.0.9.dist-info/WHEEL
quantastor_pkg-1.0.9.dist-info/top_level.txt
quantastor_pkg-1.0.9.dist-info/RECORD
