Metadata-Version: 2.1
Name: quantastor-pkg
Version: 1.0.9
Summary: QuantaStor REST API python library
Home-page: https://github.com/OSNEXUS/QSPyClient
Author: OSNEXUS Corporation
Author-email: support@osnexus.com
License: UNKNOWN
Platform: UNKNOWN
Classifier: Programming Language :: Python :: 3
Classifier: License :: OSI Approved :: BSD License
Classifier: Operating System :: OS Independent
Requires-Dist: urllib3
